exif_stripper/__init__.py
exif_stripper/cli.py
exif_stripper/exceptions.py
exif_stripper/fields.py
exif_stripper/processing.py
exif_stripper-1.2.0.dist-info/METADATA
exif_stripper-1.2.0.dist-info/WHEEL
exif_stripper-1.2.0.dist-info/entry_points.txt
exif_stripper-1.2.0.dist-info/licenses/LICENSE
exif_stripper-1.2.0.dist-info/RECORD
