Metadata-Version: 2.4
Name: exif-stripper
Version: 1.2.0
Summary: An easy-to-use tool to ensure image EXIF metadata is removed.
Project-URL: Documentation, https://github.com/stefmolin/exif-stripper
Project-URL: Homepage, https://github.com/stefmolin/exif-stripper
Project-URL: Source, https://github.com/stefmolin/exif-stripper
Author-email: Stefanie Molin <exif-stripper@stefaniemolin.com>
License-Expression: Apache-2.0
License-File: LICENSE
Keywords: exif,image processing,metadata,pre-commit
Classifier: Development Status :: 5 - Production/Stable
Classifier: Programming Language :: Python
Classifier: Programming Language :: Python :: 3 :: Only
Classifier: Programming Language :: Python :: 3.11
Classifier: Programming Language :: Python :: 3.12
Classifier: Programming Language :: Python :: 3.13
Classifier: Programming Language :: Python :: 3.14
Requires-Python: >=3.11
Requires-Dist: pillow>=12.0.0
